{
  "hello": "👋 Здравствуйте\nМы будем рады записать вас на бета-тестирование нашего приложения и поделиться с вами промокодом\nНеобходимо только подписаться на наш телеграм канал @PlayloopApp, и нажать кнопку 👇",
  "buttonCheckSub": "Проверить подписку",
  "thanksForSub": "Спасибо за подписку на @PlayloopApp!",
  "givePromo": "🥳 Ура! Промокод уже ваш!\nПромокод: WINTERGREEN\nВам доступно 3 дня бесплатной подписки Flash, доступ к озвучке сюжетных приключений настольных игр и к всем коллекциям звуков в Миксере ⚡️📦\n\nВы сможете воспользоватся промокодом сразу после получения бета доступа к приложению.",
  "signUpForTesting": "☕️ Пара шагов до тестирования атмосферных партий\nДля записи на бета-тест, пришлите свой ник/почту на сайте в ответном сообщении",
  "signUpForTestingDone": "Ваши данные доступа были сохранены, периодически мы добавляем новых пользователей для тестирования и вы уже в очереди!\nОставайтесь на связи, мы скоро вам напишем! 🎲⚔️⭐🏹🛡️🦂🐉",
  "dataUpdated": "Ваши данные доступа были обновлены.",
  "timeout": "Данные нельзя обновлять чаще 2 минут! Попробуйте попозже.",
  "dontSub": "💁‍♂️ Подпишитесь на канал\nЧтобы получить промокод и записаться на бета-тест, необходимо подписаться на наш телеграм канал @PlayloopApp",
  "errBase": "Извините, что-то пошло не так.",
  "errSub": "Извините, что-то пошло не так при проверке вашей подписки на наш телеграм канал @PlayloopApp"
}